hrbrthemes/__init__.py
hrbrthemes/theme_ipsum.py
hrbrthemes_HRBRMSTR-0.1.0.dist-info/LICENSE
hrbrthemes_HRBRMSTR-0.1.0.dist-info/METADATA
hrbrthemes_HRBRMSTR-0.1.0.dist-info/WHEEL
hrbrthemes_HRBRMSTR-0.1.0.dist-info/top_level.txt
hrbrthemes_HRBRMSTR-0.1.0.dist-info/RECORD
