Metadata-Version: 2.1
Name: hrbrthemes_HRBRMSTR
Version: 0.1.0
Summary: Opinionated Themes For plotine
Home-page: https://gitlab.com/hrbrmstr/hrbrthemes-p9
Author: boB Rudis
Author-email: boB Rudis <bob@rud.is>
Project-URL: Homepage, https://gitlab.com/hrbrmstr/hrbrthemes-p9
Project-URL: Issues, https://gitlab.com/hrbrmstr/hrbrthemes-p9/issues
Keywords: plotnine, ggplot2, themes
Classifier: Programming Language :: Python :: 3
Classifier: License :: OSI Approved :: MIT License
Classifier: Operating System :: OS Independent
Requires-Python: >=3.6
License-File: LICENSE
Requires-Dist: plotnine
